__init__.py
vargram/__init__.py
vargram/vargram.py
vargram/data/__init__.py
vargram/data/example.py
vargram/data/nextclade.py
vargram/plots/__init__.py
vargram/plots/_profile.py
vargram/plots/_profile_elements.py
vargram/plots/_profile_renderer.py
vargram/wranglers/__init__.py
vargram/wranglers/_nextclade.py
vargram/wranglers/_nextclade_cli.py
vargram/wranglers/_nextclade_utils.py
vargram/wranglers/_wrangler.py
vargram-0.4.0.dist-info/licenses/LICENSE
vargram-0.4.0.dist-info/METADATA
vargram-0.4.0.dist-info/WHEEL
vargram-0.4.0.dist-info/top_level.txt
vargram-0.4.0.dist-info/RECORD
