Metadata-Version: 2.4
Name: vargram
Version: 0.4.0
Summary: A Python visualization tool for genomic surveillance
Author: C. J. Palpal-latoc, Francis A. Tablizo
Maintainer-email: Philippine Genome Center - Core Facility for Bioinformatics <bioinformatics@pgc.up.edu.ph>
Project-URL: Repository, https://github.com/pgcbioinfo/vargram
Keywords: virus,mutations,epidemiology,visualization
Classifier: Development Status :: 4 - Beta
Classifier: Topic :: Scientific/Engineering :: Visualization
Classifier: Intended Audience :: Science/Research
Classifier: Intended Audience :: End Users/Desktop
Classifier: License :: OSI Approved :: MIT License
Classifier: Programming Language :: Python :: 3.12
Classifier: Programming Language :: Python :: 3.11
Classifier: Operating System :: OS Independent
Requires-Python: >=3.11
License-File: LICENSE
Requires-Dist: matplotlib>=3.9.2
Requires-Dist: pandas>=2.2.2
Requires-Dist: numpy>=1.26.4
Requires-Dist: regex>=2024.7.24
Requires-Dist: tabulate>=0.9.0
Requires-Dist: requests>=2.32.0
Dynamic: license-file
